Workbook

Sheet README
A1: Plantilla Business Case + Estados Financieros Proyectados (Incrementales)
A3: Objetivo: evaluar una iniciativa/proyecto con impacto financiero y vista gerencial.
A4: Flujo recomendado: Inputs → IS/CF/BS → KPIs → Business_Case → Dashboard.
A5: Editar solo celdas amarillas en Inputs.
A6: Modelo simplificado y adaptable; no reemplaza modelo contable/ERP.
A8: Preparado para portfolio / entrevistas (anonimizable).
A9: Usuario: José Joaquín Ortiz de Zevallos

Sheet Inputs
A1: Business Case Template (Proyecto / Iniciativa)
A3: Escenario | B3: Base | D3: Notas
A4: Moneda | B4: CLP | D4: Editar celdas amarillas (inputs).
A5: Año inicio | B5: 2026 | D5: Modelo simplificado para evaluación financiera.
D6: Se puede adaptar a producto, automatización, canal comercial, etc.
A8: WACC | B8: 0.12
A9: Tasa de impuesto | B9: 0.27
A10: Inflación costos | B10: 0.04
A11: Horizonte (años) | B11: 5
A12: Ingresos Año 1 | B12: 600000000
A13: Crecimiento ingresos Y2-Y5 | B13: 0.15
A14: Margen bruto % | B14: 0.55
A15: Opex fijo Año 1 | B15: 180000000
A16: Opex variable % ingresos | B16: 0.12
A17: CAPEX inicial (Año 0) | B17: 120000000
A18: CAPEX mantenimiento % ingresos | B18: 0.03
A19: Depreciación vida útil (años) | B19: 4
... A22: Inventario días | B22: 10

Sheet IS
A1: Estado de Resultados Incremental
B3: Año 0 | C3: Año 1 | D3: Año 2 | E3: Año 3 | F3: Año 4 | G3: Año 5
A4: Ingresos | B4: 0 | C4: =Inputs!$B$13 | D4: =C4*(1+Inputs!$B$14) | E4: =D4*(1+Inputs!$B$14) | F4: =E4*(1+Inputs!$B$14) | G4: =F4*(1+Inputs!$B$14)
A5: % crecimiento | B5: 0 | C5: 0 | D5: =IFERROR(D4/C4-1,0) | E5: =IFERROR(E4/D4-1,0) | F5: =IFERROR(F4/E4-1,0) | G5: =IFERROR(G4/F4-1,0)
A6: COGS | B6: =-B4*(1-Inputs!$B$15) | C6: =-C4*(1-Inputs!$B$15) | D6: =-D4*(1-Inputs!$B$15) | E6: =-E4*(1-Inputs!$B$15) | F6: =-F4*(1-Inputs!$B$15) | G6: =-G4*(1-Inputs!$B$15)
A7: Utilidad Bruta | B7: =B4+B6 | C7: =C4+C6 | D7: =D4+D6 | E7: =E4+E6 | F7: =F4+F6 | G7: =G4+G6
A8: Margen Bruto % | B8: =IFERROR(B7/B4,0) | C8: =IFERROR(C7/C4,0) | D8: =IFERROR(D7/D4,0) | E8: =IFERROR(E7/E4,0) | F8: =IFERROR(F7/F4,0) | G8: =IFERROR(G7/G4,0)
A9: Opex fijo | B9: 0 | C9: =-Inputs!$B$16 | D9: =C9*(1+Inputs!$B$10) | E9: =D9*(1+Inputs!$B$10) | F9: =E9*(1+Inputs!$B$10) | G9: =F9*(1+Inputs!$B$10)
A10: Opex variable | B10: =-B4*Inputs!$B$17 | C10: =-C4*Inputs!$B$17 | D10: =-D4*Inputs!$B$17 | E10: =-E4*Inputs!$B$17 | F10: =-F4*Inputs!$B$17 | G10: =-G4*Inputs!$B$17
A11: Opex total | B11: =B9+B10 | C11: =C9+C10 | D11: =D9+D10 | E11: =E9+E10 | F11: =F9+F10 | G11: =G9+G10
A12: EBITDA | B12: =B7+B11 | C12: =C7+C11 | D12: =D7+D11 | E12: =E7+E11 | F12: =F7+F11 | G12: =G7+G11
A13: Margen EBITDA % | B13: =IFERROR(B12/B4,0) | C13: =IFERROR(C12/C4,0) | D13: =IFERROR(D12/D4,0) | E13: =IFERROR(E12/E4,0) | F13: =IFERROR(F12/F4,0) | G13: =IFERROR(G12/G4,0)
A14: Depreciación | B14: 0 | C14: =-Inputs!$B$18/Inputs!$B$20 | D14: =C14-(D4*Inputs!$B$19/Inputs!$B$20) | E14: =D14-(E4*Inputs!$B$19/Inputs!$B$20) | F14: =E14-(F4*Inputs!$B$19/Inputs!$B$20) | G14: =F14-(G4*Inputs!$B$19/Inputs!$B$20)
A15: EBIT | B15: =B12+B14 | C15: =C12+C14 | D15: =D12+D14 | E15: =E12+E14 | F15: =F12+F14 | G15: =G12+G14
A16: Interés | B16: 0 | C16: 0 | D16: 0 | E16: 0 | F16: 0 | G16: 0
A17: EBT | B17: =B15+B16 | C17: =C15+C16 | D17: =D15+D16 | E17: =E15+E16 | F17: =F15+F16 | G17: =G15+G16
A18: Impuesto | B18: =IF(B17>0,-B17*Inputs!$B$9,0) | C18: =IF(C17>0,-C17*Inputs!$B$9,0) | D18: =IF(D17>0,-D17*Inputs!$B$9,0) | E18: =IF(E17>0,-E17*Inputs!$B$9,0) | F18: =IF(F17>0,-F17*Inputs!$B$9,0) | G18: =IF(G17>0,-G17*Inputs!$B$9,0)
A19: Resultado Neto | B19: =B17+B18 | C19: =C17+C18 | D19: =D17+D18 | E19: =E17+E18 | F19: =F17+F18 | G19: =G17+G18

Sheet CF
A1: Flujo de Caja (Incremental)
B3: Año 0 | C3: Año 1 | D3: Año 2 | E3: Año 3 | F3: Año 4 | G3: Año 5
A4: Resultado Neto | B4: =IS!B19 | C4: =IS!C19 | D4: =IS!D19 | E4: =IS!E19 | F4: =IS!F19 | G4: =IS!G19
A5: + Depreciación | B5: =-IS!B14 | C5: =-IS!C14 | D5: =-IS!D14 | E5: =-IS!E14 | F5: =-IS!F14 | G5: =-IS!G14
A6: Δ CxC | B6: 0 | C6: =-((IS!C4/365)*Inputs!$B$21-(IS!B4/365)*Inputs!$B$21) | D6: =-((IS!D4/365)*Inputs!$B$21-(IS!C4/365)*Inputs!$B$21) | E6: =-((IS!E4/365)*Inputs!$B$21-(IS!D4/365)*Inputs!$B$21) | F6: =-((IS!F4/365)*Inputs!$B$21-(IS!E4/365)*Inputs!$B$21) | G6: =-((IS!G4/365)*Inputs!$B$21-(IS!F4/365)*Inputs!$B$21)
A7: Δ Inventario | B7: 0 | C7: =-((ABS(IS!C6)/365)*Inputs!$B$23-(ABS(IS!B6)/365)*Inputs!$B$23) | D7: =-((ABS(IS!D6)/365)*Inputs!$B$23-(ABS(IS!C6)/365)*Inputs!$B$23) | E7: =-((ABS(IS!E6)/365)*Inputs!$B$23-(ABS(IS!D6)/365)*Inputs!$B$23) | F7: =-((ABS(IS!F6)/365)*Inputs!$B$23-(ABS(IS!E6)/365)*Inputs!$B$23) | G7: =-((ABS(IS!G6)/365)*Inputs!$B$23-(ABS(IS!F6)/365)*Inputs!$B$23)
A8: Δ CxP | B8: 0 | C8: =(((ABS(IS!C6)+ABS(IS!C10))/365)*Inputs!$B$22-((ABS(IS!B6)+ABS(IS!B10))/365)*Inputs!$B$22) | D8: =(((ABS(IS!D6)+ABS(IS!D10))/365)*Inputs!$B$22-((ABS(IS!C6)+ABS(IS!C10))/365)*Inputs!$B$22) | E8: =(((ABS(IS!E6)+ABS(IS!E10))/365)*Inputs!$B$22-((ABS(IS!D6)+ABS(IS!D10))/365)*Inputs!$B$22) | F8: =(((ABS(IS!F6)+ABS(IS!F10))/365)*Inputs!$B$22-((ABS(IS!E6)+ABS(IS!E10))/365)*Inputs!$B$22) | G8: =(((ABS(IS!G6)+ABS(IS!G10))/365)*Inputs!$B$22-((ABS(IS!F6)+ABS(IS!F10))/365)*Inputs!$B$22)
A9: Flujo Operacional (CFO) | B9: =SUM(B4:B8) | C9: =SUM(C4:C8) | D9: =SUM(D4:D8) | E9: =SUM(E4:E8) | F9: =SUM(F4:F8) | G9: =SUM(G4:G8)
A10: CAPEX | B10: =-Inputs!$B$18 | C10: =-IS!C4*Inputs!$B$19 | D10: =-IS!D4*Inputs!$B$19 | E10: =-IS!E4*Inputs!$B$19 | F10: =-IS!F4*Inputs!$B$19 | G10: =-IS!G4*Inputs!$B$19
A11: Flujo de Caja Libre (FCF) | B11: =B9+B10 | C11: =C9+C10 | D11: =D9+D10 | E11: =E9+E10 | F11: =F9+F10 | G11: =G9+G10
A12: Financiamiento | B12: 0 | C12: 0 | D12: 0 | E12: 0 | F12: 0 | G12: 0
A13: Flujo Neto | B13: =B11+B12 | C13: =C11+C12 | D13: =D11+D12 | E13: =E11+E12 | F13: =F11+F12 | G13: =G11+G12
A14: Caja Acumulada | B14: =B13 | C14: =B14+C13 | D14: =C14+D13 | E14: =D14+E13 | F14: =E14+F13 | G14: =F14+G13

Sheet BS
A1: Balance General (Incremental)
B3: Año 0 | C3: Año 1 | D3: Año 2 | E3: Año 3 | F3: Año 4 | G3: Año 5
A4: Caja | B4: =CF!B14 | C4: =CF!C14 | D4: =CF!D14 | E4: =CF!E14 | F4: =CF!F14 | G4: =CF!G14
A5: CxC | B5: =(IS!B4/365)*Inputs!$B$21 | C5: =(IS!C4/365)*Inputs!$B$21 | D5: =(IS!D4/365)*Inputs!$B$21 | E5: =(IS!E4/365)*Inputs!$B$21 | F5: =(IS!F4/365)*Inputs!$B$21 | G5: =(IS!G4/365)*Inputs!$B$21
A6: Inventario | B6: =(ABS(IS!B6)/365)*Inputs!$B$23 | C6: =(ABS(IS!C6)/365)*Inputs!$B$23 | D6: =(ABS(IS!D6)/365)*Inputs!$B$23 | E6: =(ABS(IS!E6)/365)*Inputs!$B$23 | F6: =(ABS(IS!F6)/365)*Inputs!$B$23 | G6: =(ABS(IS!G6)/365)*Inputs!$B$23
A7: PP&E neto | B7: 0 | C7: =Inputs!$B$18+IS!C14 | D7: =MAX(0,C7-ABS(IS!D14)+ABS(CF!D10)) | E7: =MAX(0,D7-ABS(IS!E14)+ABS(CF!E10)) | F7: =MAX(0,E7-ABS(IS!F14)+ABS(CF!F10)) | G7: =MAX(0,F7-ABS(IS!G14)+ABS(CF!G10))
A8: Total Activos | B8: =SUM(B4:B7) | C8: =SUM(C4:C7) | D8: =SUM(D4:D7) | E8: =SUM(E4:E7) | F8: =SUM(F4:F7) | G8: =SUM(G4:G7)
A9: CxP | B9: =((ABS(IS!B6)+ABS(IS!B10))/365)*Inputs!$B$22 | C9: =((ABS(IS!C6)+ABS(IS!C10))/365)*Inputs!$B$22 | D9: =((ABS(IS!D6)+ABS(IS!D10))/365)*Inputs!$B$22 | E9: =((ABS(IS!E6)+ABS(IS!E10))/365)*Inputs!$B$22 | F9: =((ABS(IS!F6)+ABS(IS!F10))/365)*Inputs!$B$22 | G9: =((ABS(IS!G6)+ABS(IS!G10))/365)*Inputs!$B$22
A10: Deuda | B10: 0 | C10: 0 | D10: 0 | E10: 0 | F10: 0 | G10: 0
A11: Total Pasivos | B11: =SUM(B9:B10) | C11: =SUM(C9:C10) | D11: =SUM(D9:D10) | E11: =SUM(E9:E10) | F11: =SUM(F9:F10) | G11: =SUM(G9:G10)
A12: Capital + Utilidades Acum. | B12: 0 | C12: =B12+IS!C19 | D12: =C12+IS!D19 | E12: =D12+IS!E19 | F12: =E12+IS!F19 | G12: =F12+IS!G19
A13: Total Patrimonio | B13: =B12 | C13: =C12 | D13: =D12 | E13: =E12 | F13: =F12 | G13: =G12
A14: Pasivos + Patrimonio | B14: =B11+B13 | C14: =C11+C13 | D14: =D11+D13 | E14: =E11+E13 | F14: =F11+F13 | G14: =G11+G13
A15: Check Cuadre | B15: =B8-B14 | C15: =C8-C14 | D15: =D8-D14 | E15: =E8-E14 | F15: =F8-F14 | G15: =G8-G14

Sheet KPIs
A1: KPIs & Evaluación
B3: Año 1 | C3: Año 2 | D3: Año 3 | E3: Año 4 | F3: Año 5
A4: Ingresos | B4: =IS!C4 | C4: =IS!D4 | D4: =IS!E4 | E4: =IS!F4 | F4: =IS!G4
A5: EBITDA | B5: =IS!C12 | C5: =IS!D12 | D5: =IS!E12 | E5: =IS!F12 | F5: =IS!G12
A6: Margen EBITDA % | B6: =IS!C13 | C6: =IS!D13 | D6: =IS!E13 | E6: =IS!F13 | F6: =IS!G13
A7: Resultado Neto | B7: =IS!C19 | C7: =IS!D19 | D7: =IS!E19 | E7: =IS!F19 | F7: =IS!G19
A8: FCF | B8: =CF!C11 | C8: =CF!D11 | D8: =CF!E11 | E8: =CF!F11 | F8: =CF!G11
A9: Caja acumulada | B9: =CF!C14 | C9: =CF!D14 | D9: =CF!E14 | E9: =CF!F14 | F9: =CF!G14
A10: ROIC simple % | B10: =IFERROR(IS!C15/(ABS(BS!C8-BS!C9)),0) | C10: =IFERROR(IS!D15/(ABS(BS!D8-BS!D9)),0) | D10: =IFERROR(IS!E15/(ABS(BS!E8-BS!E9)),0) | E10: =IFERROR(IS!F15/(ABS(BS!F8-BS!F9)),0) | F10: =IFERROR(IS!G15/(ABS(BS!G8-BS!G9)),0)

Sheet Business_Case
A1: Business Case Summary
A3: VAN (NPV) | B3: =NPV(Inputs!$B$8,CF!C11:CF!G11)+CF!B11 | D3: FCF por año
A4: TIR (IRR) | B4: =IRR(CF!B11:G11) | D4: Año 0 | E4: =CF!C11
A5: Payback (años) | B5: =MATCH(TRUE,CF!B14:G14>=0,0)-1 | D5: Año 1 | E5: =CF!D11
A6: Año break-even EBITDA | B6: =MATCH(TRUE,IS!B12:G12>0,0)-1 | D6: Año 2 | E6: =CF!E11
A7: Recomendación | B7: =IF(AND(B3>0,B4>Inputs!$B$8),"GO","REVISAR") | D7: Año 3 | E7: =CF!F11
A8: Comentarios | B8: Ajustar escenarios y revisar sensibilidad de drivers. | D8: Año 4 | E8: =CF!G11
D9: Año 5 | E9: =CF!H11

Sheet Dashboard
A1: Vista Gerencial
A3: Ingresos Año 1 | C3: EBITDA Año 1 | E3: VAN | G3: TIR
A4: =IS!C4 | C4: =IS!C12 | E4: =Business_Case!B3 | G4: =Business_Case!B4
A8: Evolución (Ingresos / EBITDA / FCF)
A9: Año 1 | B9: =KPIs!B4 | C9: =KPIs!B5 | D9: =KPIs!B8
A10: Año 2 | B10: =KPIs!C4 | C10: =KPIs!C5 | D10: =KPIs!C8
A11: Año 3 | B11: =KPIs!D4 | C11: =KPIs!D5 | D11: =KPIs!D8
A12: Año 4 | B12: =KPIs!E4 | C12: =KPIs!E5 | D12: =KPIs!E8
A13: Año 5 | B13: =KPIs!F4 | C13: =KPIs!F5 | D13: =KPIs!F8
