Workbook

Sheet README
A1: FP&A Corporativo desde Libro Diario (Template)
A3: Objetivo: transformar asientos contables (libro diario) en EEFF + KPIs + vista gerencial.
A4: Pegar asientos en "Libro_Diario" y mantener "Plan_Cuentas" + "Mapeo".
A5: Las vistas son mensuales; se pueden extender.
A6: Template para uso interno / corporativo (sueldos, caja, pagos, CxC, CxP).

Sheet Parametros
A1: Parámetros
A3: Año | B3: 2026
A4: Mes inicio | B4: 1
A5: Mes fin | B5: 12
A6: Moneda | B6: CLP

Sheet Plan_Cuentas
A1: Cuenta_ID | B1: Nombre_Cuenta | C1: Naturaleza | D1: Tipo_N1 | E1: Tipo_N2 | F1: Tipo_N3 | G1: Clasificación EEFF | H1: Orden
A2: 1101 | B2: Caja y Bancos | C2: Deudora | D2: Activo | E2: Corriente | F2: Caja | G2: Balance | H2: 10
A3: 1201 | B3: Cuentas por Cobrar Clientes | C3: Deudora | D3: Activo | E3: Corriente | F3: CxC | G3: Balance | H3: 20
A4: 1301 | B4: Inventarios | C4: Deudora | D4: Activo | E4: Corriente | F4: Inventario | G4: Balance | H4: 30
A5: 1501 | B5: Propiedad Planta y Equipo | C5: Deudora | D5: Activo | E5: No corriente | F5: PP&E | G5: Balance | H5: 40
A6: 2101 | B6: Cuentas por Pagar Proveedores | C6: Acreedora | D6: Pasivo | E6: Corriente | F6: CxP | G6: Balance | H6: 110
A7: 2201 | B7: Remuneraciones por Pagar | C7: Acreedora | D7: Pasivo | E7: Corriente | F7: Sueldos por pagar | G7: Balance | H7: 120
A8: 2301 | B8: Impuestos por Pagar | C8: Acreedora | D8: Pasivo | E8: Corriente | F8: Impuestos por pagar | G8: Balance | H8: 130
A9: 3101 | B9: Capital | C9: Acreedora | D9: Patrimonio | E9: Patrimonio | F9: Capital | G9: Balance | H9: 210
A10: 4101 | B10: Ingresos por Ventas | C10: Acreedora | D10: Resultado | E10: Ingresos | F10: Ventas | G10: Resultados | H10: 310
A11: 5101 | B11: Costo de Ventas | C11: Deudora | D11: Resultado | E11: Costos | F11: COGS | G11: Resultados | H11: 410
A12: 6101 | B12: Sueldos y Salarios | C12: Deudora | D12: Resultado | E12: Opex | F12: Sueldos | G12: Resultados | H12: 510
A13: 6201 | B13: Arriendos | C13: Deudora | D13: Resultado | E13: Opex | F13: Arriendos | G13: Resultados | H13: 520
... A16: 7101 | B16: Gasto Financiero | C16: Deudora | D16: Resultado | E16: No operacional | F16: Intereses | G16: Resultados | H16: 610

Sheet Libro_Diario
A1: Fecha | B1: Periodo | C1: Asiento_ID | D1: Descripción | E1: Cuenta_ID | F1: Centro_Costo | G1: Tercero | H1: Debe | I1: Haber | J1: Referencia | K1: Neto | L1: Tipo_N1 | M1: Tipo_N2 | N1: Tipo_N3 | O1: Nombre_Cuenta | P1: Naturaleza
A2: 2026-01-02 | B2: 2026-01 | C2: A0001 | D2: Aporte de capital | E2: 1101 | H2: 50000000 | I2: 0 | K2: =H2-I2 | L2: =IFERROR(VLOOKUP(E2,Plan_Cuentas!$A:$H,4,FALSE),"") | M2: =IFERROR(VLOOKUP(E2,Plan_Cuentas!$A:$H,5,FALSE),"") | N2: =IFERROR(VLOOKUP(E2,Plan_Cuentas!$A:$H,6,FALSE),"") | O2: =IFERROR(VLOOKUP(E2,Plan_Cuentas!$A:$H,2,FALSE),"") | P2: =IFERROR(VLOOKUP(E2,Plan_Cuentas!$A:$H,3,FALSE),"")
A3: 2026-01-02 | B3: 2026-01 | C3: A0001 | D3: Aporte de capital | E3: 3101 | H3: 0 | I3: 50000000 | K3: =H3-I3 | L3: =IFERROR(VLOOKUP(E3,Plan_Cuentas!$A:$H,4,FALSE),"") | M3: =IFERROR(VLOOKUP(E3,Plan_Cuentas!$A:$H,5,FALSE),"") | N3: =IFERROR(VLOOKUP(E3,Plan_Cuentas!$A:$H,6,FALSE),"") | O3: =IFERROR(VLOOKUP(E3,Plan_Cuentas!$A:$H,2,FALSE),"") | P3: =IFERROR(VLOOKUP(E3,Plan_Cuentas!$A:$H,3,FALSE),"")
A4: 2026-01-10 | B4: 2026-01 | C4: A0002 | D4: Venta al crédito | E4: 1201 | F4: Comercial | G4: Cliente A | H4: 18000000 | I4: 0 | J4: FV001 | K4: =H4-I4 | L4: =IFERROR(VLOOKUP(E4,Plan_Cuentas!$A:$H,4,FALSE),"") | M4: =IFERROR(VLOOKUP(E4,Plan_Cuentas!$A:$H,5,FALSE),"") | N4: =IFERROR(VLOOKUP(E4,Plan_Cuentas!$A:$H,6,FALSE),"") | O4: =IFERROR(VLOOKUP(E4,Plan_Cuentas!$A:$H,2,FALSE),"") | P4: =IFERROR(VLOOKUP(E4,Plan_Cuentas!$A:$H,3,FALSE),"")
A5: 2026-01-10 | B5: 2026-01 | C5: A0002 | D5: Venta al crédito | E5: 4101 | F5: Comercial | G5: Cliente A | H5: 0 | I5: 18000000 | J5: FV001 | K5: =H5-I5 | L5: =IFERROR(VLOOKUP(E5,Plan_Cuentas!$A:$H,4,FALSE),"") | M5: =IFERROR(VLOOKUP(E5,Plan_Cuentas!$A:$H,5,FALSE),"") | N5: =IFERROR(VLOOKUP(E5,Plan_Cuentas!$A:$H,6,FALSE),"") | O5: =IFERROR(VLOOKUP(E5,Plan_Cuentas!$A:$H,2,FALSE),"") | P5: =IFERROR(VLOOKUP(E5,Plan_Cuentas!$A:$H,3,FALSE),"")
A6: 2026-01-15 | B6: 2026-01 | C6: A0003 | D6: Costo de ventas | E6: 5101 | F6: Operaciones | G6: Proveedor X | H6: 7000000 | I6: 0 | J6: OC001 | K6: =H6-I6 | L6: =IFERROR(VLOOKUP(E6,Plan_Cuentas!$A:$H,4,FALSE),"") | M6: =IFERROR(VLOOKUP(E6,Plan_Cuentas!$A:$H,5,FALSE),"") | N6: =IFERROR(VLOOKUP(E6,Plan_Cuentas!$A:$H,6,FALSE),"") | O6: =IFERROR(VLOOKUP(E6,Plan_Cuentas!$A:$H,2,FALSE),"") | P6: =IFERROR(VLOOKUP(E6,Plan_Cuentas!$A:$H,3,FALSE),"")
A7: 2026-01-15 | B7: 2026-01 | C7: A0003 | D7: Costo de ventas | E7: 2101 | F7: Operaciones | G7: Proveedor X | H7: 0 | I7: 7000000 | J7: OC001 | K7: =H7-I7 | L7: =IFERROR(VLOOKUP(E7,Plan_Cuentas!$A:$H,4,FALSE),"") | M7: =IFERROR(VLOOKUP(E7,Plan_Cuentas!$A:$H,5,FALSE),"") | N7: =IFERROR(VLOOKUP(E7,Plan_Cuentas!$A:$H,6,FALSE),"") | O7: =IFERROR(VLOOKUP(E7,Plan_Cuentas!$A:$H,2,FALSE),"") | P7: =IFERROR(VLOOKUP(E7,Plan_Cuentas!$A:$H,3,FALSE),"")
A8: 2026-01-31 | B8: 2026-01 | C8: A0004 | D8: Devengo sueldos | E8: 6101 | F8: Administración | G8: Personal | H8: 4500000 | I8: 0 | J8: PAY01 | K8: =H8-I8 | L8: =IFERROR(VLOOKUP(E8,Plan_Cuentas!$A:$H,4,FALSE),"") | M8: =IFERROR(VLOOKUP(E8,Plan_Cuentas!$A:$H,5,FALSE),"") | N8: =IFERROR(VLOOKUP(E8,Plan_Cuentas!$A:$H,6,FALSE),"") | O8: =IFERROR(VLOOKUP(E8,Plan_Cuentas!$A:$H,2,FALSE),"") | P8: =IFERROR(VLOOKUP(E8,Plan_Cuentas!$A:$H,3,FALSE),"")
A9: 2026-01-31 | B9: 2026-01 | C9: A0004 | D9: Devengo sueldos | E9: 2201 | F9: Administración | G9: Personal | H9: 0 | I9: 4500000 | J9: PAY01 | K9: =H9-I9 | L9: =IFERROR(VLOOKUP(E9,Plan_Cuentas!$A:$H,4,FALSE),"") | M9: =IFERROR(VLOOKUP(E9,Plan_Cuentas!$A:$H,5,FALSE),"") | N9: =IFERROR(VLOOKUP(E9,Plan_Cuentas!$A:$H,6,FALSE),"") | O9: =IFERROR(VLOOKUP(E9,Plan_Cuentas!$A:$H,2,FALSE),"") | P9: =IFERROR(VLOOKUP(E9,Plan_Cuentas!$A:$H,3,FALSE),"")
A10: 2026-01-28 | B10: 2026-01 | C10: A0005 | D10: Cobranza clientes | E10: 1101 | F10: Tesorería | G10: Cliente A | H10: 8000000 | I10: 0 | J10: RC001 | K10: =H10-I10 | L10: =IFERROR(VLOOKUP(E10,Plan_Cuentas!$A:$H,4,FALSE),"") | M10: =IFERROR(VLOOKUP(E10,Plan_Cuentas!$A:$H,5,FALSE),"") | N10: =IFERROR(VLOOKUP(E10,Plan_Cuentas!$A:$H,6,FALSE),"") | O10: =IFERROR(VLOOKUP(E10,Plan_Cuentas!$A:$H,2,FALSE),"") | P10: =IFERROR(VLOOKUP(E10,Plan_Cuentas!$A:$H,3,FALSE),"")
A11: 2026-01-28 | B11: 2026-01 | C11: A0005 | D11: Cobranza clientes | E11: 1201 | F11: Tesorería | G11: Cliente A | H11: 0 | I11: 8000000 | J11: RC001 | K11: =H11-I11 | L11: =IFERROR(VLOOKUP(E11,Plan_Cuentas!$A:$H,4,FALSE),"") | M11: =IFERROR(VLOOKUP(E11,Plan_Cuentas!$A:$H,5,FALSE),"") | N11: =IFERROR(VLOOKUP(E11,Plan_Cuentas!$A:$H,6,FALSE),"") | O11: =IFERROR(VLOOKUP(E11,Plan_Cuentas!$A:$H,2,FALSE),"") | P11: =IFERROR(VLOOKUP(E11,Plan_Cuentas!$A:$H,3,FALSE),"")
A12: 2026-01-29 | B12: 2026-01 | C12: A0006 | D12: Pago proveedor | E12: 2101 | F12: Tesorería | G12: Proveedor X | H12: 3000000 | I12: 0 | J12: EP001 | K12: =H12-I12 | L12: =IFERROR(VLOOKUP(E12,Plan_Cuentas!$A:$H,4,FALSE),"") | M12: =IFERROR(VLOOKUP(E12,Plan_Cuentas!$A:$H,5,FALSE),"") | N12: =IFERROR(VLOOKUP(E12,Plan_Cuentas!$A:$H,6,FALSE),"") | O12: =IFERROR(VLOOKUP(E12,Plan_Cuentas!$A:$H,2,FALSE),"") | P12: =IFERROR(VLOOKUP(E12,Plan_Cuentas!$A:$H,3,FALSE),"")
A13: 2026-01-29 | B13: 2026-01 | C13: A0006 | D13: Pago proveedor | E13: 1101 | F13: Tesorería | G13: Proveedor X | H13: 0 | I13: 3000000 | J13: EP001 | K13: =H13-I13 | L13: =IFERROR(VLOOKUP(E13,Plan_Cuentas!$A:$H,4,FALSE),"") | M13: =IFERROR(VLOOKUP(E13,Plan_Cuentas!$A:$H,5,FALSE),"") | N13: =IFERROR(VLOOKUP(E13,Plan_Cuentas!$A:$H,6,FALSE),"") | O13: =IFERROR(VLOOKUP(E13,Plan_Cuentas!$A:$H,2,FALSE),"") | P13: =IFERROR(VLOOKUP(E13,Plan_Cuentas!$A:$H,3,FALSE),"")
A14: 2026-02-10 | B14: 2026-02 | C14: A0007 | D14: Venta al crédito | E14: 1201 | F14: Comercial | G14: Cliente B | H14: 22000000 | I14: 0 | J14: FV002 | K14: =H14-I14 | L14: =IFERROR(VLOOKUP(E14,Plan_Cuentas!$A:$H,4,FALSE),"") | M14: =IFERROR(VLOOKUP(E14,Plan_Cuentas!$A:$H,5,FALSE),"") | N14: =IFERROR(VLOOKUP(E14,Plan_Cuentas!$A:$H,6,FALSE),"") | O14: =IFERROR(VLOOKUP(E14,Plan_Cuentas!$A:$H,2,FALSE),"") | P14: =IFERROR(VLOOKUP(E14,Plan_Cuentas!$A:$H,3,FALSE),"")
A15: 2026-02-10 | B15: 2026-02 | C15: A0007 | D15: Venta al crédito | E15: 4101 | F15: Comercial | G15: Cliente B | H15: 0 | I15: 22000000 | J15: FV002 | K15: =H15-I15 | L15: =IFERROR(VLOOKUP(E15,Plan_Cuentas!$A:$H,4,FALSE),"") | M15: =IFERROR(VLOOKUP(E15,Plan_Cuentas!$A:$H,5,FALSE),"") | N15: =IFERROR(VLOOKUP(E15,Plan_Cuentas!$A:$H,6,FALSE),"") | O15: =IFERROR(VLOOKUP(E15,Plan_Cuentas!$A:$H,2,FALSE),"") | P15: =IFERROR(VLOOKUP(E15,Plan_Cuentas!$A:$H,3,FALSE),"")
... A17: 2026-02-28 | B17: 2026-02 | C17: A0008 | D17: Devengo sueldos | E17: 2201 | F17: Administración | G17: Personal | H17: 0 | I17: 4600000 | J17: PAY02 | K17: =H17-I17 | L17: =IFERROR(VLOOKUP(E17,Plan_Cuentas!$A:$H,4,FALSE),"") | M17: =IFERROR(VLOOKUP(E17,Plan_Cuentas!$A:$H,5,FALSE),"") | N17: =IFERROR(VLOOKUP(E17,Plan_Cuentas!$A:$H,6,FALSE),"") | O17: =IFERROR(VLOOKUP(E17,Plan_Cuentas!$A:$H,2,FALSE),"") | P17: =IFERROR(VLOOKUP(E17,Plan_Cuentas!$A:$H,3,FALSE),"")

Sheet Mapeo
A1: Line_Item | B1: Estado | C1: Signo | D1: Filtro_Tipo_N1 | E1: Filtro_Tipo_N2 | F1: Filtro_Tipo_N3 | G1: Cuenta_ID_específica (opcional) | H1: Orden
A2: Caja y Bancos | B2: Balance | C2: 1 | D2: Activo | F2: Caja | H2: 10
A3: Cuentas por Cobrar | B3: Balance | C3: 1 | D3: Activo | F3: CxC | H3: 20
A4: Inventarios | B4: Balance | C4: 1 | D4: Activo | F4: Inventario | H4: 30
A5: PP&E | B5: Balance | C5: 1 | D5: Activo | F5: PP&E | H5: 40
A6: Cuentas por Pagar | B6: Balance | C6: -1 | D6: Pasivo | F6: CxP | H6: 110
A7: Remuneraciones por Pagar | B7: Balance | C7: -1 | D7: Pasivo | F7: Sueldos por pagar | H7: 120
A8: Impuestos por Pagar | B8: Balance | C8: -1 | D8: Pasivo | F8: Impuestos por pagar | H8: 130
A9: Capital | B9: Balance | C9: -1 | D9: Patrimonio | F9: Capital | H9: 210
A10: Ventas | B10: Resultados | C10: -1 | D10: Resultado | E10: Ingresos | H10: 310
A11: Costo de Ventas | B11: Resultados | C11: 1 | D11: Resultado | E11: Costos | H11: 410
A12: Sueldos | B12: Resultados | C12: 1 | D12: Resultado | E12: Opex | F12: Sueldos | H12: 510
A13: Arriendos | B13: Resultados | C13: 1 | D13: Resultado | E13: Opex | F13: Arriendos | H13: 520
A14: Servicios | B14: Resultados | C14: 1 | D14: Resultado | E14: Opex | F14: Servicios | H14: 530
A15: Depreciación | B15: Resultados | C15: 1 | D15: Resultado | E15: Opex | F15: Depreciación | H15: 540
A16: Gasto Financiero | B16: Resultados | C16: 1 | D16: Resultado | E16: No operacional | H16: 610

Sheet Balance
A1: Balance General (mensual) desde Libro Diario
B3: 2026-01 | C3: 2026-02 | D3: 2026-03 | E3: 2026-04 | F3: 2026-05 | G3: 2026-06 | H3: 2026-07 | I3: 2026-08 | J3: 2026-09 | K3: 2026-10 | L3: 2026-11 | M3: 2026-12
A4: Caja y Bancos | B4: =SUMIFS(Libro_Diario!$K:$K,Libro_Diario!$B:$B,"<=2026-01",Libro_Diario!$N:$N,"Caja")*1 | C4: =SUMIFS(Libro_Diario!$K:$K,Libro_Diario!$B:$B,"<=2026-02",Libro_Diario!$N:$N,"Caja")*1 | D4: =SUMIFS(Libro_Diario!$K:$K,Libro_Diario!$B:$B,"<=2026-03",Libro_Diario!$N:$N,"Caja")*1 | E4: =SUMIFS(Libro_Diario!$K:$K,Libro_Diario!$B:$B,"<=2026-04",Libro_Diario!$N:$N,"Caja")*1 | F4: =SUMIFS(Libro_Diario!$K:$K,Libro_Diario!$B:$B,"<=2026-05",Libro_Diario!$N:$N,"Caja")*1 | G4: =SUMIFS(Libro_Diario!$K:$K,Libro_Diario!$B:$B,"<=2026-06",Libro_Diario!$N:$N,"Caja")*1 | H4: =SUMIFS(Libro_Diario!$K:$K,Libro_Diario!$B:$B,"<=2026-07",Libro_Diario!$N:$N,"Caja")*1 | I4: =SUMIFS(Libro_Diario!$K:$K,Libro_Diario!$B:$B,"<=2026-08",Libro_Diario!$N:$N,"Caja")*1 | J4: =SUMIFS(Libro_Diario!$K:$K,Libro_Diario!$B:$B,"<=2026-09",Libro_Diario!$N:$N,"Caja")*1 | K4: =SUMIFS(Libro_Diario!$K:$K,Libro_Diario!$B:$B,"<=2026-10",Libro_Diario!$N:$N,"Caja")*1 | L4: =SUMIFS(Libro_Diario!$K:$K,Libro_Diario!$B:$B,"<=2026-11",Libro_Diario!$N:$N,"Caja")*1 | M4: =SUMIFS(Libro_Diario!$K:$K,Libro_Diario!$B:$B,"<=2026-12",Libro_Diario!$N:$N,"Caja")*1
A5: Cuentas por Cobrar | B5: =SUMIFS(Libro_Diario!$K:$K,Libro_Diario!$B:$B,"<=2026-01",Libro_Diario!$N:$N,"CxC")*1 | C5: =SUMIFS(Libro_Diario!$K:$K,Libro_Diario!$B:$B,"<=2026-02",Libro_Diario!$N:$N,"CxC")*1 | D5: =SUMIFS(Libro_Diario!$K:$K,Libro_Diario!$B:$B,"<=2026-03",Libro_Diario!$N:$N,"CxC")*1 | E5: =SUMIFS(Libro_Diario!$K:$K,Libro_Diario!$B:$B,"<=2026-04",Libro_Diario!$N:$N,"CxC")*1 | F5: =SUMIFS(Libro_Diario!$K:$K,Libro_Diario!$B:$B,"<=2026-05",Libro_Diario!$N:$N,"CxC")*1 | G5: =SUMIFS(Libro_Diario!$K:$K,Libro_Diario!$B:$B,"<=2026-06",Libro_Diario!$N:$N,"CxC")*1 | H5: =SUMIFS(Libro_Diario!$K:$K,Libro_Diario!$B:$B,"<=2026-07",Libro_Diario!$N:$N,"CxC")*1 | I5: =SUMIFS(Libro_Diario!$K:$K,Libro_Diario!$B:$B,"<=2026-08",Libro_Diario!$N:$N,"CxC")*1 | J5: =SUMIFS(Libro_Diario!$K:$K,Libro_Diario!$B:$B,"<=2026-09",Libro_Diario!$N:$N,"CxC")*1 | K5: =SUMIFS(Libro_Diario!$K:$K,Libro_Diario!$B:$B,"<=2026-10",Libro_Diario!$N:$N,"CxC")*1 | L5: =SUMIFS(Libro_Diario!$K:$K,Libro_Diario!$B:$B,"<=2026-11",Libro_Diario!$N:$N,"CxC")*1 | M5: =SUMIFS(Libro_Diario!$K:$K,Libro_Diario!$B:$B,"<=2026-12",Libro_Diario!$N:$N,"CxC")*1
A6: Inventarios | B6: =SUMIFS(Libro_Diario!$K:$K,Libro_Diario!$B:$B,"<=2026-01",Libro_Diario!$N:$N,"Inventario")*1 | C6: =SUMIFS(Libro_Diario!$K:$K,Libro_Diario!$B:$B,"<=2026-02",Libro_Diario!$N:$N,"Inventario")*1 | D6: =SUMIFS(Libro_Diario!$K:$K,Libro_Diario!$B:$B,"<=2026-03",Libro_Diario!$N:$N,"Inventario")*1 | E6: =SUMIFS(Libro_Diario!$K:$K,Libro_Diario!$B:$B,"<=2026-04",Libro_Diario!$N:$N,"Inventario")*1 | F6: =SUMIFS(Libro_Diario!$K:$K,Libro_Diario!$B:$B,"<=2026-05",Libro_Diario!$N:$N,"Inventario")*1 | G6: =SUMIFS(Libro_Diario!$K:$K,Libro_Diario!$B:$B,"<=2026-06",Libro_Diario!$N:$N,"Inventario")*1 | H6: =SUMIFS(Libro_Diario!$K:$K,Libro_Diario!$B:$B,"<=2026-07",Libro_Diario!$N:$N,"Inventario")*1 | I6: =SUMIFS(Libro_Diario!$K:$K,Libro_Diario!$B:$B,"<=2026-08",Libro_Diario!$N:$N,"Inventario")*1 | J6: =SUMIFS(Libro_Diario!$K:$K,Libro_Diario!$B:$B,"<=2026-09",Libro_Diario!$N:$N,"Inventario")*1 | K6: =SUMIFS(Libro_Diario!$K:$K,Libro_Diario!$B:$B,"<=2026-10",Libro_Diario!$N:$N,"Inventario")*1 | L6: =SUMIFS(Libro_Diario!$K:$K,Libro_Diario!$B:$B,"<=2026-11",Libro_Diario!$N:$N,"Inventario")*1 | M6: =SUMIFS(Libro_Diario!$K:$K,Libro_Diario!$B:$B,"<=2026-12",Libro_Diario!$N:$N,"Inventario")*1
A7: PP&E | B7: =SUMIFS(Libro_Diario!$K:$K,Libro_Diario!$B:$B,"<=2026-01",Libro_Diario!$N:$N,"PP&E")*1 | C7: =SUMIFS(Libro_Diario!$K:$K,Libro_Diario!$B:$B,"<=2026-02",Libro_Diario!$N:$N,"PP&E")*1 | D7: =SUMIFS(Libro_Diario!$K:$K,Libro_Diario!$B:$B,"<=2026-03",Libro_Diario!$N:$N,"PP&E")*1 | E7: =SUMIFS(Libro_Diario!$K:$K,Libro_Diario!$B:$B,"<=2026-04",Libro_Diario!$N:$N,"PP&E")*1 | F7: =SUMIFS(Libro_Diario!$K:$K,Libro_Diario!$B:$B,"<=2026-05",Libro_Diario!$N:$N,"PP&E")*1 | G7: =SUMIFS(Libro_Diario!$K:$K,Libro_Diario!$B:$B,"<=2026-06",Libro_Diario!$N:$N,"PP&E")*1 | H7: =SUMIFS(Libro_Diario!$K:$K,Libro_Diario!$B:$B,"<=2026-07",Libro_Diario!$N:$N,"PP&E")*1 | I7: =SUMIFS(Libro_Diario!$K:$K,Libro_Diario!$B:$B,"<=2026-08",Libro_Diario!$N:$N,"PP&E")*1 | J7: =SUMIFS(Libro_Diario!$K:$K,Libro_Diario!$B:$B,"<=2026-09",Libro_Diario!$N:$N,"PP&E")*1 | K7: =SUMIFS(Libro_Diario!$K:$K,Libro_Diario!$B:$B,"<=2026-10",Libro_Diario!$N:$N,"PP&E")*1 | L7: =SUMIFS(Libro_Diario!$K:$K,Libro_Diario!$B:$B,"<=2026-11",Libro_Diario!$N:$N,"PP&E")*1 | M7: =SUMIFS(Libro_Diario!$K:$K,Libro_Diario!$B:$B,"<=2026-12",Libro_Diario!$N:$N,"PP&E")*1
A8: Total Activos | B8: =SUM(B4:B7) | C8: =SUM(C4:C7) | D8: =SUM(D4:D7) | E8: =SUM(E4:E7) | F8: =SUM(F4:F7) | G8: =SUM(G4:G7) | H8: =SUM(H4:H7) | I8: =SUM(I4:I7) | ... M8: =SUM(M4:M7)
A10: Cuentas por Pagar | B10: =SUMIFS(Libro_Diario!$K:$K,Libro_Diario!$B:$B,"<=2026-01",Libro_Diario!$N:$N,"CxP")*-1 | C10: =SUMIFS(Libro_Diario!$K:$K,Libro_Diario!$B:$B,"<=2026-02",Libro_Diario!$N:$N,"CxP")*-1 | D10: =SUMIFS(Libro_Diario!$K:$K,Libro_Diario!$B:$B,"<=2026-03",Libro_Diario!$N:$N,"CxP")*-1 | E10: =SUMIFS(Libro_Diario!$K:$K,Libro_Diario!$B:$B,"<=2026-04",Libro_Diario!$N:$N,"CxP")*-1 | F10: =SUMIFS(Libro_Diario!$K:$K,Libro_Diario!$B:$B,"<=2026-05",Libro_Diario!$N:$N,"CxP")*-1 | G10: =SUMIFS(Libro_Diario!$K:$K,Libro_Diario!$B:$B,"<=2026-06",Libro_Diario!$N:$N,"CxP")*-1 | H10: =SUMIFS(Libro_Diario!$K:$K,Libro_Diario!$B:$B,"<=2026-07",Libro_Diario!$N:$N,"CxP")*-1 | I10: =SUMIFS(Libro_Diario!$K:$K,Libro_Diario!$B:$B,"<=2026-08",Libro_Diario!$N:$N,"CxP")*-1 | J10: =SUMIFS(Libro_Diario!$K:$K,Libro_Diario!$B:$B,"<=2026-09",Libro_Diario!$N:$N,"CxP")*-1 | K10: =SUMIFS(Libro_Diario!$K:$K,Libro_Diario!$B:$B,"<=2026-10",Libro_Diario!$N:$N,"CxP")*-1 | L10: =SUMIFS(Libro_Diario!$K:$K,Libro_Diario!$B:$B,"<=2026-11",Libro_Diario!$N:$N,"CxP")*-1 | M10: =SUMIFS(Libro_Diario!$K:$K,Libro_Diario!$B:$B,"<=2026-12",Libro_Diario!$N:$N,"CxP")*-1
A11: Remuneraciones por Pagar | B11: =SUMIFS(Libro_Diario!$K:$K,Libro_Diario!$B:$B,"<=2026-01",Libro_Diario!$N:$N,"Sueldos por pagar")*-1 | C11: =SUMIFS(Libro_Diario!$K:$K,Libro_Diario!$B:$B,"<=2026-02",Libro_Diario!$N:$N,"Sueldos por pagar")*-1 | D11: =SUMIFS(Libro_Diario!$K:$K,Libro_Diario!$B:$B,"<=2026-03",Libro_Diario!$N:$N,"Sueldos por pagar")*-1 | E11: =SUMIFS(Libro_Diario!$K:$K,Libro_Diario!$B:$B,"<=2026-04",Libro_Diario!$N:$N,"Sueldos por pagar")*-1 | F11: =SUMIFS(Libro_Diario!$K:$K,Libro_Diario!$B:$B,"<=2026-05",Libro_Diario!$N:$N,"Sueldos por pagar")*-1 | G11: =SUMIFS(Libro_Diario!$K:$K,Libro_Diario!$B:$B,"<=2026-06",Libro_Diario!$N:$N,"Sueldos por pagar")*-1 | H11: =SUMIFS(Libro_Diario!$K:$K,Libro_Diario!$B:$B,"<=2026-07",Libro_Diario!$N:$N,"Sueldos por pagar")*-1 | I11: =SUMIFS(Libro_Diario!$K:$K,Libro_Diario!$B:$B,"<=2026-08",Libro_Diario!$N:$N,"Sueldos por pagar")*-1 | J11: =SUMIFS(Libro_Diario!$K:$K,Libro_Diario!$B:$B,"<=2026-09",Libro_Diario!$N:$N,"Sueldos por pagar")*-1 | K11: =SUMIFS(Libro_Diario!$K:$K,Libro_Diario!$B:$B,"<=2026-10",Libro_Diario!$N:$N,"Sueldos por pagar")*-1 | L11: =SUMIFS(Libro_Diario!$K:$K,Libro_Diario!$B:$B,"<=2026-11",Libro_Diario!$N:$N,"Sueldos por pagar")*-1 | M11: =SUMIFS(Libro_Diario!$K:$K,Libro_Diario!$B:$B,"<=2026-12",Libro_Diario!$N:$N,"Sueldos por pagar")*-1
A12: Impuestos por Pagar | B12: =SUMIFS(Libro_Diario!$K:$K,Libro_Diario!$B:$B,"<=2026-01",Libro_Diario!$N:$N,"Impuestos por pagar")*-1 | C12: =SUMIFS(Libro_Diario!$K:$K,Libro_Diario!$B:$B,"<=2026-02",Libro_Diario!$N:$N,"Impuestos por pagar")*-1 | D12: =SUMIFS(Libro_Diario!$K:$K,Libro_Diario!$B:$B,"<=2026-03",Libro_Diario!$N:$N,"Impuestos por pagar")*-1 | E12: =SUMIFS(Libro_Diario!$K:$K,Libro_Diario!$B:$B,"<=2026-04",Libro_Diario!$N:$N,"Impuestos por pagar")*-1 | F12: =SUMIFS(Libro_Diario!$K:$K,Libro_Diario!$B:$B,"<=2026-05",Libro_Diario!$N:$N,"Impuestos por pagar")*-1 | G12: =SUMIFS(Libro_Diario!$K:$K,Libro_Diario!$B:$B,"<=2026-06",Libro_Diario!$N:$N,"Impuestos por pagar")*-1 | H12: =SUMIFS(Libro_Diario!$K:$K,Libro_Diario!$B:$B,"<=2026-07",Libro_Diario!$N:$N,"Impuestos por pagar")*-1 | I12: =SUMIFS(Libro_Diario!$K:$K,Libro_Diario!$B:$B,"<=2026-08",Libro_Diario!$N:$N,"Impuestos por pagar")*-1 | J12: =SUMIFS(Libro_Diario!$K:$K,Libro_Diario!$B:$B,"<=2026-09",Libro_Diario!$N:$N,"Impuestos por pagar")*-1 | K12: =SUMIFS(Libro_Diario!$K:$K,Libro_Diario!$B:$B,"<=2026-10",Libro_Diario!$N:$N,"Impuestos por pagar")*-1 | L12: =SUMIFS(Libro_Diario!$K:$K,Libro_Diario!$B:$B,"<=2026-11",Libro_Diario!$N:$N,"Impuestos por pagar")*-1 | M12: =SUMIFS(Libro_Diario!$K:$K,Libro_Diario!$B:$B,"<=2026-12",Libro_Diario!$N:$N,"Impuestos por pagar")*-1
A13: Total Pasivos | B13: =SUM(B10:B12) | C13: =SUM(C10:C12) | D13: =SUM(D10:D12) | E13: =SUM(E10:E12) | F13: =SUM(F10:F12) | G13: =SUM(G10:G12) | H13: =SUM(H10:H12) | I13: =SUM(I10:I12) | ... M13: =SUM(M10:M12)
A15: Capital | B15: =SUMIFS(Libro_Diario!$K:$K,Libro_Diario!$B:$B,"<=2026-01",Libro_Diario!$N:$N,"Capital")*-1 | C15: =SUMIFS(Libro_Diario!$K:$K,Libro_Diario!$B:$B,"<=2026-02",Libro_Diario!$N:$N,"Capital")*-1 | D15: =SUMIFS(Libro_Diario!$K:$K,Libro_Diario!$B:$B,"<=2026-03",Libro_Diario!$N:$N,"Capital")*-1 | E15: =SUMIFS(Libro_Diario!$K:$K,Libro_Diario!$B:$B,"<=2026-04",Libro_Diario!$N:$N,"Capital")*-1 | F15: =SUMIFS(Libro_Diario!$K:$K,Libro_Diario!$B:$B,"<=2026-05",Libro_Diario!$N:$N,"Capital")*-1 | G15: =SUMIFS(Libro_Diario!$K:$K,Libro_Diario!$B:$B,"<=2026-06",Libro_Diario!$N:$N,"Capital")*-1 | H15: =SUMIFS(Libro_Diario!$K:$K,Libro_Diario!$B:$B,"<=2026-07",Libro_Diario!$N:$N,"Capital")*-1 | I15: =SUMIFS(Libro_Diario!$K:$K,Libro_Diario!$B:$B,"<=2026-08",Libro_Diario!$N:$N,"Capital")*-1 | J15: =SUMIFS(Libro_Diario!$K:$K,Libro_Diario!$B:$B,"<=2026-09",Libro_Diario!$N:$N,"Capital")*-1 | K15: =SUMIFS(Libro_Diario!$K:$K,Libro_Diario!$B:$B,"<=2026-10",Libro_Diario!$N:$N,"Capital")*-1 | L15: =SUMIFS(Libro_Diario!$K:$K,Libro_Diario!$B:$B,"<=2026-11",Libro_Diario!$N:$N,"Capital")*-1 | M15: =SUMIFS(Libro_Diario!$K:$K,Libro_Diario!$B:$B,"<=2026-12",Libro_Diario!$N:$N,"Capital")*-1
A16: Resultado acumulado | B16: =SUM(Resultados!$B$17:B$17) | C16: =SUM(Resultados!$B$17:C$17) | D16: =SUM(Resultados!$B$17:D$17) | E16: =SUM(Resultados!$B$17:E$17) | F16: =SUM(Resultados!$B$17:F$17) | G16: =SUM(Resultados!$B$17:G$17) | H16: =SUM(Resultados!$B$17:H$17) | I16: =SUM(Resultados!$B$17:I$17) | ... M16: =SUM(Resultados!$B$17:M$17)
A17: Patrimonio | B17: =SUM(B15:B16) | C17: =SUM(C15:C16) | D17: =SUM(D15:D16) | E17: =SUM(E15:E16) | F17: =SUM(F15:F16) | G17: =SUM(G15:G16) | H17: =SUM(H15:H16) | I17: =SUM(I15:I16) | ... M17: =SUM(M15:M16)
A18: Pasivo + Patrimonio | B18: =B13+B17 | C18: =C13+C17 | D18: =D13+D17 | E18: =E13+E17 | F18: =F13+F17 | G18: =G13+G17 | H18: =H13+H17 | I18: =I13+I17 | ... M18: =M13+M17
A19: Check | B19: =B8-B18 | C19: =C8-C18 | D19: =D8-D18 | E19: =E8-E18 | F19: =F8-F18 | G19: =G8-G18 | H19: =H8-H18 | I19: =I8-I18 | ... M19: =M8-M18

Sheet Resultados
A1: Estado de Resultados (mensual) desde Libro Diario
B3: 2026-01 | C3: 2026-02 | D3: 2026-03 | E3: 2026-04 | F3: 2026-05 | G3: 2026-06 | H3: 2026-07 | I3: 2026-08 | J3: 2026-09 | K3: 2026-10 | L3: 2026-11 | M3: 2026-12
A4: Ventas | B4: =SUMIFS(Libro_Diario!$K:$K,Libro_Diario!$B:$B,"2026-01",Libro_Diario!$M:$M,"Ingresos")*-1 | C4: =SUMIFS(Libro_Diario!$K:$K,Libro_Diario!$B:$B,"2026-02",Libro_Diario!$M:$M,"Ingresos")*-1 | D4: =SUMIFS(Libro_Diario!$K:$K,Libro_Diario!$B:$B,"2026-03",Libro_Diario!$M:$M,"Ingresos")*-1 | E4: =SUMIFS(Libro_Diario!$K:$K,Libro_Diario!$B:$B,"2026-04",Libro_Diario!$M:$M,"Ingresos")*-1 | F4: =SUMIFS(Libro_Diario!$K:$K,Libro_Diario!$B:$B,"2026-05",Libro_Diario!$M:$M,"Ingresos")*-1 | G4: =SUMIFS(Libro_Diario!$K:$K,Libro_Diario!$B:$B,"2026-06",Libro_Diario!$M:$M,"Ingresos")*-1 | H4: =SUMIFS(Libro_Diario!$K:$K,Libro_Diario!$B:$B,"2026-07",Libro_Diario!$M:$M,"Ingresos")*-1 | I4: =SUMIFS(Libro_Diario!$K:$K,Libro_Diario!$B:$B,"2026-08",Libro_Diario!$M:$M,"Ingresos")*-1 | J4: =SUMIFS(Libro_Diario!$K:$K,Libro_Diario!$B:$B,"2026-09",Libro_Diario!$M:$M,"Ingresos")*-1 | K4: =SUMIFS(Libro_Diario!$K:$K,Libro_Diario!$B:$B,"2026-10",Libro_Diario!$M:$M,"Ingresos")*-1 | L4: =SUMIFS(Libro_Diario!$K:$K,Libro_Diario!$B:$B,"2026-11",Libro_Diario!$M:$M,"Ingresos")*-1 | M4: =SUMIFS(Libro_Diario!$K:$K,Libro_Diario!$B:$B,"2026-12",Libro_Diario!$M:$M,"Ingresos")*-1
A5: Costo de Ventas | B5: =SUMIFS(Libro_Diario!$K:$K,Libro_Diario!$B:$B,"2026-01",Libro_Diario!$M:$M,"Costos")*1 | C5: =SUMIFS(Libro_Diario!$K:$K,Libro_Diario!$B:$B,"2026-02",Libro_Diario!$M:$M,"Costos")*1 | D5: =SUMIFS(Libro_Diario!$K:$K,Libro_Diario!$B:$B,"2026-03",Libro_Diario!$M:$M,"Costos")*1 | E5: =SUMIFS(Libro_Diario!$K:$K,Libro_Diario!$B:$B,"2026-04",Libro_Diario!$M:$M,"Costos")*1 | F5: =SUMIFS(Libro_Diario!$K:$K,Libro_Diario!$B:$B,"2026-05",Libro_Diario!$M:$M,"Costos")*1 | G5: =SUMIFS(Libro_Diario!$K:$K,Libro_Diario!$B:$B,"2026-06",Libro_Diario!$M:$M,"Costos")*1 | H5: =SUMIFS(Libro_Diario!$K:$K,Libro_Diario!$B:$B,"2026-07",Libro_Diario!$M:$M,"Costos")*1 | I5: =SUMIFS(Libro_Diario!$K:$K,Libro_Diario!$B:$B,"2026-08",Libro_Diario!$M:$M,"Costos")*1 | J5: =SUMIFS(Libro_Diario!$K:$K,Libro_Diario!$B:$B,"2026-09",Libro_Diario!$M:$M,"Costos")*1 | K5: =SUMIFS(Libro_Diario!$K:$K,Libro_Diario!$B:$B,"2026-10",Libro_Diario!$M:$M,"Costos")*1 | L5: =SUMIFS(Libro_Diario!$K:$K,Libro_Diario!$B:$B,"2026-11",Libro_Diario!$M:$M,"Costos")*1 | M5: =SUMIFS(Libro_Diario!$K:$K,Libro_Diario!$B:$B,"2026-12",Libro_Diario!$M:$M,"Costos")*1
A6: Utilidad Bruta | B6: =B4-B5 | C6: =C4-C5 | D6: =D4-D5 | E6: =E4-E5 | F6: =F4-F5 | G6: =G4-G5 | H6: =H4-H5 | I6: =I4-I5 | ... M6: =M4-M5
A7: Sueldos | B7: =SUMIFS(Libro_Diario!$K:$K,Libro_Diario!$B:$B,"2026-01",Libro_Diario!$N:$N,"Sueldos")*1 | C7: =SUMIFS(Libro_Diario!$K:$K,Libro_Diario!$B:$B,"2026-02",Libro_Diario!$N:$N,"Sueldos")*1 | D7: =SUMIFS(Libro_Diario!$K:$K,Libro_Diario!$B:$B,"2026-03",Libro_Diario!$N:$N,"Sueldos")*1 | E7: =SUMIFS(Libro_Diario!$K:$K,Libro_Diario!$B:$B,"2026-04",Libro_Diario!$N:$N,"Sueldos")*1 | F7: =SUMIFS(Libro_Diario!$K:$K,Libro_Diario!$B:$B,"2026-05",Libro_Diario!$N:$N,"Sueldos")*1 | G7: =SUMIFS(Libro_Diario!$K:$K,Libro_Diario!$B:$B,"2026-06",Libro_Diario!$N:$N,"Sueldos")*1 | H7: =SUMIFS(Libro_Diario!$K:$K,Libro_Diario!$B:$B,"2026-07",Libro_Diario!$N:$N,"Sueldos")*1 | I7: =SUMIFS(Libro_Diario!$K:$K,Libro_Diario!$B:$B,"2026-08",Libro_Diario!$N:$N,"Sueldos")*1 | J7: =SUMIFS(Libro_Diario!$K:$K,Libro_Diario!$B:$B,"2026-09",Libro_Diario!$N:$N,"Sueldos")*1 | K7: =SUMIFS(Libro_Diario!$K:$K,Libro_Diario!$B:$B,"2026-10",Libro_Diario!$N:$N,"Sueldos")*1 | L7: =SUMIFS(Libro_Diario!$K:$K,Libro_Diario!$B:$B,"2026-11",Libro_Diario!$N:$N,"Sueldos")*1 | M7: =SUMIFS(Libro_Diario!$K:$K,Libro_Diario!$B:$B,"2026-12",Libro_Diario!$N:$N,"Sueldos")*1
A8: Arriendos | B8: =SUMIFS(Libro_Diario!$K:$K,Libro_Diario!$B:$B,"2026-01",Libro_Diario!$N:$N,"Arriendos")*1 | C8: =SUMIFS(Libro_Diario!$K:$K,Libro_Diario!$B:$B,"2026-02",Libro_Diario!$N:$N,"Arriendos")*1 | D8: =SUMIFS(Libro_Diario!$K:$K,Libro_Diario!$B:$B,"2026-03",Libro_Diario!$N:$N,"Arriendos")*1 | E8: =SUMIFS(Libro_Diario!$K:$K,Libro_Diario!$B:$B,"2026-04",Libro_Diario!$N:$N,"Arriendos")*1 | F8: =SUMIFS(Libro_Diario!$K:$K,Libro_Diario!$B:$B,"2026-05",Libro_Diario!$N:$N,"Arriendos")*1 | G8: =SUMIFS(Libro_Diario!$K:$K,Libro_Diario!$B:$B,"2026-06",Libro_Diario!$N:$N,"Arriendos")*1 | H8: =SUMIFS(Libro_Diario!$K:$K,Libro_Diario!$B:$B,"2026-07",Libro_Diario!$N:$N,"Arriendos")*1 | I8: =SUMIFS(Libro_Diario!$K:$K,Libro_Diario!$B:$B,"2026-08",Libro_Diario!$N:$N,"Arriendos")*1 | J8: =SUMIFS(Libro_Diario!$K:$K,Libro_Diario!$B:$B,"2026-09",Libro_Diario!$N:$N,"Arriendos")*1 | K8: =SUMIFS(Libro_Diario!$K:$K,Libro_Diario!$B:$B,"2026-10",Libro_Diario!$N:$N,"Arriendos")*1 | L8: =SUMIFS(Libro_Diario!$K:$K,Libro_Diario!$B:$B,"2026-11",Libro_Diario!$N:$N,"Arriendos")*1 | M8: =SUMIFS(Libro_Diario!$K:$K,Libro_Diario!$B:$B,"2026-12",Libro_Diario!$N:$N,"Arriendos")*1
A9: Servicios | B9: =SUMIFS(Libro_Diario!$K:$K,Libro_Diario!$B:$B,"2026-01",Libro_Diario!$N:$N,"Servicios")*1 | C9: =SUMIFS(Libro_Diario!$K:$K,Libro_Diario!$B:$B,"2026-02",Libro_Diario!$N:$N,"Servicios")*1 | D9: =SUMIFS(Libro_Diario!$K:$K,Libro_Diario!$B:$B,"2026-03",Libro_Diario!$N:$N,"Servicios")*1 | E9: =SUMIFS(Libro_Diario!$K:$K,Libro_Diario!$B:$B,"2026-04",Libro_Diario!$N:$N,"Servicios")*1 | F9: =SUMIFS(Libro_Diario!$K:$K,Libro_Diario!$B:$B,"2026-05",Libro_Diario!$N:$N,"Servicios")*1 | G9: =SUMIFS(Libro_Diario!$K:$K,Libro_Diario!$B:$B,"2026-06",Libro_Diario!$N:$N,"Servicios")*1 | H9: =SUMIFS(Libro_Diario!$K:$K,Libro_Diario!$B:$B,"2026-07",Libro_Diario!$N:$N,"Servicios")*1 | I9: =SUMIFS(Libro_Diario!$K:$K,Libro_Diario!$B:$B,"2026-08",Libro_Diario!$N:$N,"Servicios")*1 | J9: =SUMIFS(Libro_Diario!$K:$K,Libro_Diario!$B:$B,"2026-09",Libro_Diario!$N:$N,"Servicios")*1 | K9: =SUMIFS(Libro_Diario!$K:$K,Libro_Diario!$B:$B,"2026-10",Libro_Diario!$N:$N,"Servicios")*1 | L9: =SUMIFS(Libro_Diario!$K:$K,Libro_Diario!$B:$B,"2026-11",Libro_Diario!$N:$N,"Servicios")*1 | M9: =SUMIFS(Libro_Diario!$K:$K,Libro_Diario!$B:$B,"2026-12",Libro_Diario!$N:$N,"Servicios")*1
A10: Depreciación | B10: =SUMIFS(Libro_Diario!$K:$K,Libro_Diario!$B:$B,"2026-01",Libro_Diario!$N:$N,"Depreciación")*1 | C10: =SUMIFS(Libro_Diario!$K:$K,Libro_Diario!$B:$B,"2026-02",Libro_Diario!$N:$N,"Depreciación")*1 | D10: =SUMIFS(Libro_Diario!$K:$K,Libro_Diario!$B:$B,"2026-03",Libro_Diario!$N:$N,"Depreciación")*1 | E10: =SUMIFS(Libro_Diario!$K:$K,Libro_Diario!$B:$B,"2026-04",Libro_Diario!$N:$N,"Depreciación")*1 | F10: =SUMIFS(Libro_Diario!$K:$K,Libro_Diario!$B:$B,"2026-05",Libro_Diario!$N:$N,"Depreciación")*1 | G10: =SUMIFS(Libro_Diario!$K:$K,Libro_Diario!$B:$B,"2026-06",Libro_Diario!$N:$N,"Depreciación")*1 | H10: =SUMIFS(Libro_Diario!$K:$K,Libro_Diario!$B:$B,"2026-07",Libro_Diario!$N:$N,"Depreciación")*1 | I10: =SUMIFS(Libro_Diario!$K:$K,Libro_Diario!$B:$B,"2026-08",Libro_Diario!$N:$N,"Depreciación")*1 | J10: =SUMIFS(Libro_Diario!$K:$K,Libro_Diario!$B:$B,"2026-09",Libro_Diario!$N:$N,"Depreciación")*1 | K10: =SUMIFS(Libro_Diario!$K:$K,Libro_Diario!$B:$B,"2026-10",Libro_Diario!$N:$N,"Depreciación")*1 | L10: =SUMIFS(Libro_Diario!$K:$K,Libro_Diario!$B:$B,"2026-11",Libro_Diario!$N:$N,"Depreciación")*1 | M10: =SUMIFS(Libro_Diario!$K:$K,Libro_Diario!$B:$B,"2026-12",Libro_Diario!$N:$N,"Depreciación")*1
A11: Opex | B11: =SUM(B7:B10) | C11: =SUM(C7:C10) | D11: =SUM(D7:D10) | E11: =SUM(E7:E10) | F11: =SUM(F7:F10) | G11: =SUM(G7:G10) | H11: =SUM(H7:H10) | I11: =SUM(I7:I10) | ... M11: =SUM(M7:M10)
A12: EBITDA | B12: =B6-B11+B10 | C12: =C6-C11+C10 | D12: =D6-D11+D10 | E12: =E6-E11+E10 | F12: =F6-F11+F10 | G12: =G6-G11+G10 | H12: =H6-H11+H10 | I12: =I6-I11+I10 | ... M12: =M6-M11+M10
A13: Gasto Financiero | B13: =SUMIFS(Libro_Diario!$K:$K,Libro_Diario!$B:$B,"2026-01",Libro_Diario!$M:$M,"No operacional")*1 | C13: =SUMIFS(Libro_Diario!$K:$K,Libro_Diario!$B:$B,"2026-02",Libro_Diario!$M:$M,"No operacional")*1 | D13: =SUMIFS(Libro_Diario!$K:$K,Libro_Diario!$B:$B,"2026-03",Libro_Diario!$M:$M,"No operacional")*1 | E13: =SUMIFS(Libro_Diario!$K:$K,Libro_Diario!$B:$B,"2026-04",Libro_Diario!$M:$M,"No operacional")*1 | F13: =SUMIFS(Libro_Diario!$K:$K,Libro_Diario!$B:$B,"2026-05",Libro_Diario!$M:$M,"No operacional")*1 | G13: =SUMIFS(Libro_Diario!$K:$K,Libro_Diario!$B:$B,"2026-06",Libro_Diario!$M:$M,"No operacional")*1 | H13: =SUMIFS(Libro_Diario!$K:$K,Libro_Diario!$B:$B,"2026-07",Libro_Diario!$M:$M,"No operacional")*1 | I13: =SUMIFS(Libro_Diario!$K:$K,Libro_Diario!$B:$B,"2026-08",Libro_Diario!$M:$M,"No operacional")*1 | J13: =SUMIFS(Libro_Diario!$K:$K,Libro_Diario!$B:$B,"2026-09",Libro_Diario!$M:$M,"No operacional")*1 | K13: =SUMIFS(Libro_Diario!$K:$K,Libro_Diario!$B:$B,"2026-10",Libro_Diario!$M:$M,"No operacional")*1 | L13: =SUMIFS(Libro_Diario!$K:$K,Libro_Diario!$B:$B,"2026-11",Libro_Diario!$M:$M,"No operacional")*1 | M13: =SUMIFS(Libro_Diario!$K:$K,Libro_Diario!$B:$B,"2026-12",Libro_Diario!$M:$M,"No operacional")*1
A14: EBT | B14: =B6-B11-B13 | C14: =C6-C11-C13 | D14: =D6-D11-D13 | E14: =E6-E11-E13 | F14: =F6-F11-F13 | G14: =G6-G11-G13 | H14: =H6-H11-H13 | I14: =I6-I11-I13 | ... M14: =M6-M11-M13
A15: Impuesto (placeholder) | B15: =IF(B14>0,B14*0.27,0) | C15: =IF(C14>0,C14*0.27,0) | D15: =IF(D14>0,D14*0.27,0) | E15: =IF(E14>0,E14*0.27,0) | F15: =IF(F14>0,F14*0.27,0) | G15: =IF(G14>0,G14*0.27,0) | H15: =IF(H14>0,H14*0.27,0) | I15: =IF(I14>0,I14*0.27,0) | ... M15: =IF(M14>0,M14*0.27,0)
A16: Resultado Neto | B16: =B14-B15 | C16: =C14-C15 | D16: =D14-D15 | E16: =E14-E15 | F16: =F14-F15 | G16: =G14-G15 | H16: =H14-H15 | I16: =I14-I15 | ... M16: =M14-M15

Sheet Flujo_Caja
A1: Flujo de Caja (directo simplificado)
B3: 2026-01 | C3: 2026-02 | D3: 2026-03 | E3: 2026-04 | F3: 2026-05 | G3: 2026-06 | H3: 2026-07 | I3: 2026-08 | J3: 2026-09 | K3: 2026-10 | L3: 2026-11 | M3: 2026-12
A4: Cobros clientes (caja) | B4: =SUMIFS(Libro_Diario!$H:$H,Libro_Diario!$B:$B,"2026-01",Libro_Diario!$E:$E,"1101",Libro_Diario!$D:$D,"*Cobranza*") | C4: =SUMIFS(Libro_Diario!$H:$H,Libro_Diario!$B:$B,"2026-02",Libro_Diario!$E:$E,"1101",Libro_Diario!$D:$D,"*Cobranza*") | D4: =SUMIFS(Libro_Diario!$H:$H,Libro_Diario!$B:$B,"2026-03",Libro_Diario!$E:$E,"1101",Libro_Diario!$D:$D,"*Cobranza*") | E4: =SUMIFS(Libro_Diario!$H:$H,Libro_Diario!$B:$B,"2026-04",Libro_Diario!$E:$E,"1101",Libro_Diario!$D:$D,"*Cobranza*") | F4: =SUMIFS(Libro_Diario!$H:$H,Libro_Diario!$B:$B,"2026-05",Libro_Diario!$E:$E,"1101",Libro_Diario!$D:$D,"*Cobranza*") | G4: =SUMIFS(Libro_Diario!$H:$H,Libro_Diario!$B:$B,"2026-06",Libro_Diario!$E:$E,"1101",Libro_Diario!$D:$D,"*Cobranza*") | H4: =SUMIFS(Libro_Diario!$H:$H,Libro_Diario!$B:$B,"2026-07",Libro_Diario!$E:$E,"1101",Libro_Diario!$D:$D,"*Cobranza*") | I4: =SUMIFS(Libro_Diario!$H:$H,Libro_Diario!$B:$B,"2026-08",Libro_Diario!$E:$E,"1101",Libro_Diario!$D:$D,"*Cobranza*") | J4: =SUMIFS(Libro_Diario!$H:$H,Libro_Diario!$B:$B,"2026-09",Libro_Diario!$E:$E,"1101",Libro_Diario!$D:$D,"*Cobranza*") | K4: =SUMIFS(Libro_Diario!$H:$H,Libro_Diario!$B:$B,"2026-10",Libro_Diario!$E:$E,"1101",Libro_Diario!$D:$D,"*Cobranza*") | L4: =SUMIFS(Libro_Diario!$H:$H,Libro_Diario!$B:$B,"2026-11",Libro_Diario!$E:$E,"1101",Libro_Diario!$D:$D,"*Cobranza*") | M4: =SUMIFS(Libro_Diario!$H:$H,Libro_Diario!$B:$B,"2026-12",Libro_Diario!$E:$E,"1101",Libro_Diario!$D:$D,"*Cobranza*")
A5: Pagos proveedores | B5: =SUMIFS(Libro_Diario!$H:$H,Libro_Diario!$B:$B,"2026-01",Libro_Diario!$E:$E,"2101") | C5: =SUMIFS(Libro_Diario!$H:$H,Libro_Diario!$B:$B,"2026-02",Libro_Diario!$E:$E,"2101") | D5: =SUMIFS(Libro_Diario!$H:$H,Libro_Diario!$B:$B,"2026-03",Libro_Diario!$E:$E,"2101") | E5: =SUMIFS(Libro_Diario!$H:$H,Libro_Diario!$B:$B,"2026-04",Libro_Diario!$E:$E,"2101") | F5: =SUMIFS(Libro_Diario!$H:$H,Libro_Diario!$B:$B,"2026-05",Libro_Diario!$E:$E,"2101") | G5: =SUMIFS(Libro_Diario!$H:$H,Libro_Diario!$B:$B,"2026-06",Libro_Diario!$E:$E,"2101") | H5: =SUMIFS(Libro_Diario!$H:$H,Libro_Diario!$B:$B,"2026-07",Libro_Diario!$E:$E,"2101") | I5: =SUMIFS(Libro_Diario!$H:$H,Libro_Diario!$B:$B,"2026-08",Libro_Diario!$E:$E,"2101") | J5: =SUMIFS(Libro_Diario!$H:$H,Libro_Diario!$B:$B,"2026-09",Libro_Diario!$E:$E,"2101") | K5: =SUMIFS(Libro_Diario!$H:$H,Libro_Diario!$B:$B,"2026-10",Libro_Diario!$E:$E,"2101") | L5: =SUMIFS(Libro_Diario!$H:$H,Libro_Diario!$B:$B,"2026-11",Libro_Diario!$E:$E,"2101") | M5: =SUMIFS(Libro_Diario!$H:$H,Libro_Diario!$B:$B,"2026-12",Libro_Diario!$E:$E,"2101")
A6: Pagos remuneraciones | B6: =SUMIFS(Libro_Diario!$H:$H,Libro_Diario!$B:$B,"2026-01",Libro_Diario!$E:$E,"2201") | C6: =SUMIFS(Libro_Diario!$H:$H,Libro_Diario!$B:$B,"2026-02",Libro_Diario!$E:$E,"2201") | D6: =SUMIFS(Libro_Diario!$H:$H,Libro_Diario!$B:$B,"2026-03",Libro_Diario!$E:$E,"2201") | E6: =SUMIFS(Libro_Diario!$H:$H,Libro_Diario!$B:$B,"2026-04",Libro_Diario!$E:$E,"2201") | F6: =SUMIFS(Libro_Diario!$H:$H,Libro_Diario!$B:$B,"2026-05",Libro_Diario!$E:$E,"2201") | G6: =SUMIFS(Libro_Diario!$H:$H,Libro_Diario!$B:$B,"2026-06",Libro_Diario!$E:$E,"2201") | H6: =SUMIFS(Libro_Diario!$H:$H,Libro_Diario!$B:$B,"2026-07",Libro_Diario!$E:$E,"2201") | I6: =SUMIFS(Libro_Diario!$H:$H,Libro_Diario!$B:$B,"2026-08",Libro_Diario!$E:$E,"2201") | J6: =SUMIFS(Libro_Diario!$H:$H,Libro_Diario!$B:$B,"2026-09",Libro_Diario!$E:$E,"2201") | K6: =SUMIFS(Libro_Diario!$H:$H,Libro_Diario!$B:$B,"2026-10",Libro_Diario!$E:$E,"2201") | L6: =SUMIFS(Libro_Diario!$H:$H,Libro_Diario!$B:$B,"2026-11",Libro_Diario!$E:$E,"2201") | M6: =SUMIFS(Libro_Diario!$H:$H,Libro_Diario!$B:$B,"2026-12",Libro_Diario!$E:$E,"2201")
A7: Otros cobros/pagos netos | B7: =SUMIFS(Libro_Diario!$K:$K,Libro_Diario!$B:$B,"2026-01",Libro_Diario!$E:$E,"1101")-B4+B5+B6 | C7: =SUMIFS(Libro_Diario!$K:$K,Libro_Diario!$B:$B,"2026-02",Libro_Diario!$E:$E,"1101")-C4+C5+C6 | D7: =SUMIFS(Libro_Diario!$K:$K,Libro_Diario!$B:$B,"2026-03",Libro_Diario!$E:$E,"1101")-D4+D5+D6 | E7: =SUMIFS(Libro_Diario!$K:$K,Libro_Diario!$B:$B,"2026-04",Libro_Diario!$E:$E,"1101")-E4+E5+E6 | F7: =SUMIFS(Libro_Diario!$K:$K,Libro_Diario!$B:$B,"2026-05",Libro_Diario!$E:$E,"1101")-F4+F5+F6 | G7: =SUMIFS(Libro_Diario!$K:$K,Libro_Diario!$B:$B,"2026-06",Libro_Diario!$E:$E,"1101")-G4+G5+G6 | H7: =SUMIFS(Libro_Diario!$K:$K,Libro_Diario!$B:$B,"2026-07",Libro_Diario!$E:$E,"1101")-H4+H5+H6 | I7: =SUMIFS(Libro_Diario!$K:$K,Libro_Diario!$B:$B,"2026-08",Libro_Diario!$E:$E,"1101")-I4+I5+I6 | J7: =SUMIFS(Libro_Diario!$K:$K,Libro_Diario!$B:$B,"2026-09",Libro_Diario!$E:$E,"1101")-J4+J5+J6 | K7: =SUMIFS(Libro_Diario!$K:$K,Libro_Diario!$B:$B,"2026-10",Libro_Diario!$E:$E,"1101")-K4+K5+K6 | L7: =SUMIFS(Libro_Diario!$K:$K,Libro_Diario!$B:$B,"2026-11",Libro_Diario!$E:$E,"1101")-L4+L5+L6 | M7: =SUMIFS(Libro_Diario!$K:$K,Libro_Diario!$B:$B,"2026-12",Libro_Diario!$E:$E,"1101")-M4+M5+M6
A8: Flujo Operacional | B8: =B4-B5-B6+B7 | C8: =C4-C5-C6+C7 | D8: =D4-D5-D6+D7 | E8: =E4-E5-E6+E7 | F8: =F4-F5-F6+F7 | G8: =G4-G5-G6+G7 | H8: =H4-H5-H6+H7 | I8: =I4-I5-I6+I7 | ... M8: =M4-M5-M6+M7
A9: CAPEX pagado | B9: 0 | C9: 0 | D9: 0 | E9: 0 | F9: 0 | G9: 0 | H9: 0 | I9: 0 | J9: 0 | K9: 0 | L9: 0 | M9: 0
A10: Flujo Neto | B10: =B8-B9 | C10: =C8-C9 | D10: =D8-D9 | E10: =E8-E9 | F10: =F8-F9 | G10: =G8-G9 | H10: =H8-H9 | I10: =I8-I9 | ... M10: =M8-M9
A11: Saldo Inicial Caja | B11: 0 | C11: =B12 | D11: =C12 | E11: =D12 | F11: =E12 | G11: =F12 | H11: =G12 | I11: =H12 | J11: =I12 | ... M11: =L12
A12: Saldo Final Caja | B12: =B11+B10 | C12: =C11+C10 | D12: =D11+D10 | E12: =E11+E10 | F12: =F11+F10 | G12: =G11+G10 | H12: =H11+H10 | I12: =I11+I10 | ... M12: =M11+M10
A13: Check vs Balance | B13: =B12-Balance!B4 | C13: =C12-Balance!C4 | D13: =D12-Balance!D4 | E13: =E12-Balance!E4 | F13: =F12-Balance!F4 | G13: =G12-Balance!G4 | H13: =H12-Balance!H4 | I13: =I12-Balance!I4 | ... M13: =M12-Balance!M4

Sheet KPIs
A1: KPIs Corporativos (mensual)
B3: 2026-01 | C3: 2026-02 | D3: 2026-03 | E3: 2026-04 | F3: 2026-05 | G3: 2026-06 | H3: 2026-07 | I3: 2026-08 | J3: 2026-09 | K3: 2026-10 | L3: 2026-11 | M3: 2026-12
A4: Ventas | B4: =Resultados!B4 | C4: =Resultados!C4 | D4: =Resultados!D4 | E4: =Resultados!E4 | F4: =Resultados!F4 | G4: =Resultados!G4 | H4: =Resultados!H4 | I4: =Resultados!I4 | ... M4: =Resultados!M4
A5: Margen Bruto % | B5: =IFERROR(Resultados!B6/Resultados!B4,0) | C5: =IFERROR(Resultados!C6/Resultados!C4,0) | D5: =IFERROR(Resultados!D6/Resultados!D4,0) | E5: =IFERROR(Resultados!E6/Resultados!E4,0) | F5: =IFERROR(Resultados!F6/Resultados!F4,0) | G5: =IFERROR(Resultados!G6/Resultados!G4,0) | H5: =IFERROR(Resultados!H6/Resultados!H4,0) | I5: =IFERROR(Resultados!I6/Resultados!I4,0) | ... M5: =IFERROR(Resultados!M6/Resultados!M4,0)
A6: Margen EBITDA % | B6: =IFERROR(Resultados!B12/Resultados!B4,0) | C6: =IFERROR(Resultados!C12/Resultados!C4,0) | D6: =IFERROR(Resultados!D12/Resultados!D4,0) | E6: =IFERROR(Resultados!E12/Resultados!E4,0) | F6: =IFERROR(Resultados!F12/Resultados!F4,0) | G6: =IFERROR(Resultados!G12/Resultados!G4,0) | H6: =IFERROR(Resultados!H12/Resultados!H4,0) | I6: =IFERROR(Resultados!I12/Resultados!I4,0) | ... M6: =IFERROR(Resultados!M12/Resultados!M4,0)
A7: Resultado Neto | B7: =Resultados!B16 | C7: =Resultados!C16 | D7: =Resultados!D16 | E7: =Resultados!E16 | F7: =Resultados!F16 | G7: =Resultados!G16 | H7: =Resultados!H16 | I7: =Resultados!I16 | ... M7: =Resultados!M16
A8: Caja Final | B8: =Balance!B4 | C8: =Balance!C4 | D8: =Balance!D4 | E8: =Balance!E4 | F8: =Balance!F4 | G8: =Balance!G4 | H8: =Balance!H4 | I8: =Balance!I4 | ... M8: =Balance!M4
A9: CxC | B9: =Balance!B5 | C9: =Balance!C5 | D9: =Balance!D5 | E9: =Balance!E5 | F9: =Balance!F5 | G9: =Balance!G5 | H9: =Balance!H5 | I9: =Balance!I5 | ... M9: =Balance!M5
A10: CxP | B10: =Balance!B10 | C10: =Balance!C10 | D10: =Balance!D10 | E10: =Balance!E10 | F10: =Balance!F10 | G10: =Balance!G10 | H10: =Balance!H10 | I10: =Balance!I10 | ... M10: =Balance!M10
A11: DSO | B11: =IFERROR((B9/Resultados!B4)*30,0) | C11: =IFERROR((C9/Resultados!C4)*30,0) | D11: =IFERROR((D9/Resultados!D4)*30,0) | E11: =IFERROR((E9/Resultados!E4)*30,0) | F11: =IFERROR((F9/Resultados!F4)*30,0) | G11: =IFERROR((G9/Resultados!G4)*30,0) | H11: =IFERROR((H9/Resultados!H4)*30,0) | I11: =IFERROR((I9/Resultados!I4)*30,0) | ... M11: =IFERROR((M9/Resultados!M4)*30,0)
A12: DPO | B12: =IFERROR((B10/Resultados!B5)*30,0) | C12: =IFERROR((C10/Resultados!C5)*30,0) | D12: =IFERROR((D10/Resultados!D5)*30,0) | E12: =IFERROR((E10/Resultados!E5)*30,0) | F12: =IFERROR((F10/Resultados!F5)*30,0) | G12: =IFERROR((G10/Resultados!G5)*30,0) | H12: =IFERROR((H10/Resultados!H5)*30,0) | I12: =IFERROR((I10/Resultados!I5)*30,0) | ... M12: =IFERROR((M10/Resultados!M5)*30,0)
A13: Razón Corriente | B13: =IFERROR((Balance!B4+Balance!B5+Balance!B6)/(Balance!B10+Balance!B11+Balance!B12),0) | C13: =IFERROR((Balance!C4+Balance!C5+Balance!C6)/(Balance!C10+Balance!C11+Balance!C12),0) | D13: =IFERROR((Balance!D4+Balance!D5+Balance!D6)/(Balance!D10+Balance!D11+Balance!D12),0) | E13: =IFERROR((Balance!E4+Balance!E5+Balance!E6)/(Balance!E10+Balance!E11+Balance!E12),0) | F13: =IFERROR((Balance!F4+Balance!F5+Balance!F6)/(Balance!F10+Balance!F11+Balance!F12),0) | G13: =IFERROR((Balance!G4+Balance!G5+Balance!G6)/(Balance!G10+Balance!G11+Balance!G12),0) | H13: =IFERROR((Balance!H4+Balance!H5+Balance!H6)/(Balance!H10+Balance!H11+Balance!H12),0) | I13: =IFERROR((Balance!I4+Balance!I5+Balance!I6)/(Balance!I10+Balance!I11+Balance!I12),0) | ... M13: =IFERROR((Balance!M4+Balance!M5+Balance!M6)/(Balance!M10+Balance!M11+Balance!M12),0)

Sheet Vista_Gerencial
A1: Vista Gerencial FP&A Corporativo
A3: Ventas mes actual | C3: Margen EBITDA | E3: Caja Final | G3: DSO
A4: =KPIs!M4 | C4: =KPIs!M6 | E4: =KPIs!M8 | G4: =KPIs!M11
A8: Mes | B8: Ventas | C8: EBITDA % | D8: Resultado Neto | E8: Caja Final
A9: 2026-01 | B9: =KPIs!C4 | C9: =KPIs!C6 | D9: =KPIs!C7 | E9: =KPIs!C8
A10: 2026-02 | B10: =KPIs!D4 | C10: =KPIs!D6 | D10: =KPIs!D7 | E10: =KPIs!D8
A11: 2026-03 | B11: =KPIs!E4 | C11: =KPIs!E6 | D11: =KPIs!E7 | E11: =KPIs!E8
A12: 2026-04 | B12: =KPIs!F4 | C12: =KPIs!F6 | D12: =KPIs!F7 | E12: =KPIs!F8
A13: 2026-05 | B13: =KPIs!G4 | C13: =KPIs!G6 | D13: =KPIs!G7 | E13: =KPIs!G8
A14: 2026-06 | B14: =KPIs!H4 | C14: =KPIs!H6 | D14: =KPIs!H7 | E14: =KPIs!H8
A15: 2026-07 | B15: =KPIs!I4 | C15: =KPIs!I6 | D15: =KPIs!I7 | E15: =KPIs!I8
A16: 2026-08 | B16: =KPIs!J4 | C16: =KPIs!J6 | D16: =KPIs!J7 | E16: =KPIs!J8
A17: 2026-09 | B17: =KPIs!K4 | C17: =KPIs!K6 | D17: =KPIs!K7 | E17: =KPIs!K8
A18: 2026-10 | B18: =KPIs!L4 | C18: =KPIs!L6 | D18: =KPIs!L7 | E18: =KPIs!L8
A19: 2026-11 | B19: =KPIs!M4 | C19: =KPIs!M6 | D19: =KPIs!M7 | E19: =KPIs!M8
A20: 2026-12 | B20: =KPIs!N4 | C20: =KPIs!N6 | D20: =KPIs!N7 | E20: =KPIs!N8

Sheet Checks
A1: Controles de Calidad
A3: Libro Diario cuadra (Debe-Haber) | B3: =SUM(Libro_Diario!H:H)-SUM(Libro_Diario!I:I)
A4: Balance check Dic | B4: =Balance!M19
A5: Flujo caja vs balance Dic | B5: =Flujo_Caja!M13
